bloxplorer/__init__.py
bloxplorer/addresses.py
bloxplorer/blocks.py
bloxplorer/constants.py
bloxplorer/exceptions.py
bloxplorer/explorer.py
bloxplorer/fees.py
bloxplorer/issued_assets.py
bloxplorer/mempool.py
bloxplorer/transactions.py
bloxplorer/utils.py
bloxplorer-0.1.12.dist-info/licenses/LICENSE
bloxplorer-0.1.12.dist-info/METADATA
bloxplorer-0.1.12.dist-info/WHEEL
bloxplorer-0.1.12.dist-info/top_level.txt
bloxplorer-0.1.12.dist-info/RECORD
