Metadata-Version: 2.4
Name: bloxplorer
Version: 0.1.12
Summary: Bitcoin and Liquid blockchain explorer
Home-page: https://github.com/valinsky/bloxplorer
Author: Vali Voicu
Author-email: contact@valinsky.me
License: MIT
Classifier: Programming Language :: Python :: 3.12
Classifier: Intended Audience :: Developers
Classifier: License :: OSI Approved :: MIT License
Classifier: Operating System :: OS Independent
License-File: LICENSE
Requires-Dist: requests
Dynamic: author
Dynamic: author-email
Dynamic: classifier
Dynamic: description
Dynamic: home-page
Dynamic: license
Dynamic: license-file
Dynamic: requires-dist
Dynamic: summary
